geoserver_mcp/__init__.py
geoserver_mcp/main.py
iflow_mcp_geoserver_mcp-0.3.0.dist-info/METADATA
iflow_mcp_geoserver_mcp-0.3.0.dist-info/WHEEL
iflow_mcp_geoserver_mcp-0.3.0.dist-info/entry_points.txt
iflow_mcp_geoserver_mcp-0.3.0.dist-info/licenses/LICENSE
iflow_mcp_geoserver_mcp-0.3.0.dist-info/RECORD
