Metadata-Version: 2.4
Name: iflow-mcp_geoserver-mcp
Version: 0.3.0
Summary: A GeoServer MCP server implementation that enhances LLM capabilities with geospatial data and mapping services via GeoServer REST API
Author: Mahdi Nazari Ashani, GeoServer MCP Contributors
License: MIT License
License-File: LICENSE
Keywords: geoserver,geospatial,llm,mcp,ogc,wfs,wms
Classifier: Development Status :: 3 - Alpha
Classifier: Intended Audience :: Developers
Classifier: License :: OSI Approved :: MIT License
Classifier: Programming Language :: Python :: 3
Classifier: Programming Language :: Python :: 3.10
Classifier: Programming Language :: Python :: 3.11
Requires-Python: >=3.10
Requires-Dist: geoserver-rest==2.9.1
Requires-Dist: mcp==1.6.0
